sarabande/CG_Coeffs.npy
sarabande/__init__.py
sarabande/boot_up.py
sarabande/calc_PCF.py
sarabande/main.py
sarabande/utils.py
sarabande-1.1.2.dist-info/LICENSE
sarabande-1.1.2.dist-info/METADATA
sarabande-1.1.2.dist-info/WHEEL
sarabande-1.1.2.dist-info/top_level.txt
sarabande-1.1.2.dist-info/RECORD
