Metadata-Version: 2.1
Name: sarabande
Version: 1.1.2
Summary: Tool for measuring 3/4 PCFs on discrete periodic data.
Home-page: https://github.com/James11222/sarabande/
Author: James Sunseri
Author-email: jamessunseri@berkeley.edu
License: MIT
Project-URL: Bug Reports, https://github.com/James11222/sarabande/issues
Project-URL: Funding, https://donate.pypi.org
Project-URL: Check out my Website!, http://www.jamessunseri.com
Project-URL: Source, https://github.com/James11222/sarabande/
Keywords: npcf,3pcf,4pcf,cosmology,hydrodynamics
Platform: any
Classifier: Development Status :: 4 - Beta
Classifier: Intended Audience :: Developers
Classifier: Topic :: Software Development :: Build Tools
Classifier: License :: OSI Approved :: MIT License
Classifier: Programming Language :: Python :: 3
Classifier: Programming Language :: Python :: 3.6
Classifier: Programming Language :: Python :: 3.7
Classifier: Programming Language :: Python :: 3.8
Classifier: Programming Language :: Python :: 3.9
Classifier: Programming Language :: Python :: 3.10
Classifier: Programming Language :: Python :: 3 :: Only
Requires-Python: >=3.6, <4
License-File: LICENSE
